{
  "DeduplicateObjects": true,
  "DeduplicationUsageThreshold": 1,
  "EnableVarints": false,
  "SortTables": true,
  "LocalityAwareSorting": true,
  "LargeTableThreshold": 8192,
  "LocalityCutoffSmall": 128,
  "LocalityCutoffLarge": 8192,
  "LocalityMinimumThreshold": 3,
  "InlineUseCountThreshold": null,
  "InlineObjectSizeThreshold": null,
  "ConditionalInlining": false,
  "PartitionedInlining": false,
  "NoOverridingPrimitiveStream": false,
  "RelativeIndexes": false,
  "TypeTagStream": true,
  "ValueStreamPerType": true,
  "ThreeByteIndices": false,
  "NullTerminatedStrings": false
}